src/ASIC/postsim/Define.v
/*
///////include///////
`include "Accumulator.v"
`include "Bias_buff.v"
`include "Controller.v"
`include "Maxpooling_or_Softmax.v"
`include "Mux_ifmap.v"
`include "Mux_of12.v"
`include "Mux_ofmap.v"
`include "Mux_psum_or_bias.v"
`include "PE_array.v"
`include "PE_vec.v"
`include "PE.v"
`include "ReLU.v"
*/
///////define////////
//ctrl
`define cnt_wid 8

//pe_wid
`define img_wid 32
`define ifmap_wid 16
`define weight_wid 16
`define bias_wid 16
`define psum_wid 32
`define PS_wid 32

//bram addr wid
`define bram_img_wid 10
`define bram_weight_wid 17
`define bram_bias_wid 8
`define bram_ofmap1_wid 13
`define bram_ofmap2_wid 12

/*
    1.img
        32b*(30*30=900)
    2.weight
        16b*76232
    3.bias
        16b*162
    4.ofmap1
        32b*(28*28*8 + 14*14*8 = 7840)
    5.ofmap2
        32b*(12*12*16 + 6*6*16  + 128 +10 = 3018)
*/

/*dig
    1.ifmap 8+8    (img: 16 + (8+8))
    2.ofmap 16+16 
    3.weight 8+8
    4.bias 8+8
*/

//buffer size
`define bias_buff_size 1
`define bias_buff_wid 1
`define weight_buff_size 84
`define weight_buff_wid 7
`define ifmap_buff_size 84
`define ifmap_buff_wid 7 
`define psum_buff_size 28
`define psum_buff_wid 5


//img & ifmap size
`define  img_h 'd30
`define  img_w 'd30
`define  img_s 'd900
`define  C1_h  'd28
`define  C1_w  'd28
`define  C1_s  'd784
`define  S2_h  'd14
`define  S2_w  'd14
`define  S2_s  'd196
`define  C3_h  'd12 
`define  C3_w  'd12
`define  C3_s  'd144
`define  S4_h  'd6 
`define  S4_w  'd6
`define  S4_s  'd36 
`define  C5_h  'd576
`define  F6_h  'd128
`define  out_h 'd10 
 

//channel num
`define img_c   'd1 
`define C1_c    'd8
`define C3_c    'd16

src/ASIC/presim/MaxPooling_or_Softmax.v
`include "Define.v"

module MaxPooling_or_Softmax (clk,rst,cnt,clear,data_in,data_out,idx);
    input clk,rst,clear;
    input [`cnt_wid-1:0] cnt;
    input signed [`psum_wid-1:0] data_in;
    output [`psum_wid-1:0] data_out;
    output reg [`PS_wid-1:0] idx;

    reg signed [`psum_wid-1:0] max;

    assign data_out = max;

    always @(posedge clk or posedge rst) begin
        if (rst) begin
            max <= 'd0;
            idx <= 'd0;
        end
        else begin
            if (clear) begin
                max <= 'd0;
                idx <= 'd0;
            end
            else begin
                if (data_in > max) begin
                    max <= data_in;
                    idx <= {24'b0,cnt};
                end
            end
        end
    end

    
endmodule

src/ASIC/testbench/tb_MaxPooling_or_Softmax.v
`include "MaxPooling_or_Softmax.v"
`timescale 1ns/10ps

`define CYCLE 10 

module tb_MaxPooling_or_Softmax;
reg clk,rst,clear;
reg [`cnt_wid-1:0] cnt;
reg signed [`psum_wid-1:0] data_in;
wire [`psum_wid-1:0] data_out;
wire [`PS_wid-1:0] idx;


always @(posedge clk or posedge rst) begin
	if (rst) begin
		cnt <= 'd0;
	end
	else begin
		if (clear) begin
			cnt <= 'd0;
		end
		else begin
			cnt <= cnt +'d1;
		end
	end
end

MaxPooling_or_Softmax maxpooling_or_softmax
(
    .clk(clk),
	.rst(rst),
	.cnt(cnt),
	.clear(clear),
	.data_in(data_in),
	.data_out(data_out),
	.idx(idx)
);

always #(`CYCLE/2) clk=~clk;

initial begin
        clk<=1'b1;
    #(`CYCLE*1) rst<=1;
    #(`CYCLE*1) rst<=0;
    #(`CYCLE*1) clear = 'd1;
    #(`CYCLE*1) clear = 'd0; data_in = 'd1;
    #(`CYCLE*1) data_in = 'd1;
    #(`CYCLE*1) data_in = 'd5;
    #(`CYCLE*1) data_in = 'd111;
    #(`CYCLE*1) data_in = 'd666;
    #(`CYCLE*1) data_in = 'd222;
    #(`CYCLE*1) data_in = -'d1;
    #(`CYCLE*1) data_in = 'd987;
    #(`CYCLE*1) clear = 'd1;
    #(`CYCLE*1) clear = 'd0; data_in = 'd6;
    #(`CYCLE*1) data_in = 'd45;
    #(`CYCLE*1) data_in = 'd999;
    #(`CYCLE*1) data_in = 'd1024;
    #(`CYCLE*1) data_in = 'd6;
    $finish;
end

initial begin
    $dumpfile("tb_MaxPooling_or_Softmax.vcd");
    $dumpvars(0, tb_MaxPooling_or_Softmax);
end

always @(*) begin
    $display($time, "data_out: %d , idx : %d",data_out,idx);
end

endmodule

src/hw/testbench/tb_MaxPooling_or_Softmax.vcd
$date
	Mon Aug 28 14:05:58 2023
$end
$version
	Icarus Verilog
$end
$timescale
	10ps
$end
$scope module tb_MaxPooling_or_Softmax $end
$var wire 32 ! idx [31:0] $end
$var wire 32 " data_out [31:0] $end
$var reg 1 # clear $end
$var reg 1 $ clk $end
$var reg 8 % cnt [7:0] $end
$var reg 32 & data_in [31:0] $end
$var reg 1 ' rst $end
$scope module maxpooling_or_softmax $end
$var wire 1 # clear $end
$var wire 1 $ clk $end
$var wire 8 ( cnt [7:0] $end
$var wire 32 ) data_in [31:0] $end
$var wire 32 * data_out [31:0] $end
$var wire 1 ' rst $end
$var reg 32 + idx [31:0] $end
$var reg 32 , max [31:0] $end
$upscope $end
$upscope $end
$enddefinitions $end
#0
$dumpvars
bx ,
bx +
bx *
bx )
bx (
x'
bx &
bx %
1$
x#
bx "
bx !
$end
#500
0$
#1000
b0 !
b0 +
b0 "
b0 *
b0 ,
b0 %
b0 (
1'
1$
#1500
0$
#2000
0'
1$
#2500
0$
#3000
1$
1#
#3500
0$
#4000
b1 %
b1 (
b1 "
b1 *
b1 ,
1$
b1 &
b1 )
0#
#4500
0$
#5000
b10 %
b10 (
1$
#5500
0$
#6000
b11 %
b11 (
b10 !
b10 +
b101 "
b101 *
b101 ,
1$
b101 &
b101 )
#6500
0$
#7000
b11 !
b11 +
b1101111 "
b1101111 *
b1101111 ,
b100 %
b100 (
1$
b1101111 &
b1101111 )
#7500
0$
#8000
b101 %
b101 (
b100 !
b100 +
b1010011010 "
b1010011010 *
b1010011010 ,
1$
b1010011010 &
b1010011010 )
#8500
0$
#9000
b110 %
b110 (
1$
b11011110 &
b11011110 )
#9500
0$
#10000
b111 %
b111 (
1$
b11111111111111111111111111111111 &
b11111111111111111111111111111111 )
#10500
0$
#11000
b111 !
b111 +
b1111011011 "
b1111011011 *
b1111011011 ,
b1000 %
b1000 (
1$
b1111011011 &
b1111011011 )
#11500
0$
#12000
b0 %
b0 (
b0 !
b0 +
b0 "
b0 *
b0 ,
1$
1#
#12500
0$
#13000
b110 "
b110 *
b110 ,
b1 %
b1 (
1$
b110 &
b110 )
0#
#13500
0$
#14000
b10 %
b10 (
b1 !
b1 +
b101101 "
b101101 *
b101101 ,
1$
b101101 &
b101101 )
#14500
0$
#15000
b10 !
b10 +
b1111100111 "
b1111100111 *
b1111100111 ,
b11 %
b11 (
1$
b1111100111 &
b1111100111 )
#15500
0$
#16000
b100 %
b100 (
b11 !
b11 +
b10000000000 "
b10000000000 *
b10000000000 ,
1$
b10000000000 &
b10000000000 )
#16500
0$
#17000
b101 %
b101 (
1$
b110 &
b110 )
