src/ASIC/postsim/Define.v
/*
///////include///////
`include "Accumulator.v"
`include "Bias_buff.v"
`include "Controller.v"
`include "Maxpooling_or_Softmax.v"
`include "Mux_ifmap.v"
`include "Mux_of12.v"
`include "Mux_ofmap.v"
`include "Mux_psum_or_bias.v"
`include "PE_array.v"
`include "PE_vec.v"
`include "PE.v"
`include "ReLU.v"
*/
///////define////////
//ctrl
`define cnt_wid 8

//pe_wid
`define img_wid 32
`define ifmap_wid 16
`define weight_wid 16
`define bias_wid 16
`define psum_wid 32
`define PS_wid 32

//bram addr wid
`define bram_img_wid 10
`define bram_weight_wid 17
`define bram_bias_wid 8
`define bram_ofmap1_wid 13
`define bram_ofmap2_wid 12

/*
    1.img
        32b*(30*30=900)
    2.weight
        16b*76232
    3.bias
        16b*162
    4.ofmap1
        32b*(28*28*8 + 14*14*8 = 7840)
    5.ofmap2
        32b*(12*12*16 + 6*6*16  + 128 +10 = 3018)
*/

/*dig
    1.ifmap 8+8    (img: 16 + (8+8))
    2.ofmap 16+16 
    3.weight 8+8
    4.bias 8+8
*/

//buffer size
`define bias_buff_size 1
`define bias_buff_wid 1
`define weight_buff_size 84
`define weight_buff_wid 7
`define ifmap_buff_size 84
`define ifmap_buff_wid 7 
`define psum_buff_size 28
`define psum_buff_wid 5


//img & ifmap size
`define  img_h 'd30
`define  img_w 'd30
`define  img_s 'd900
`define  C1_h  'd28
`define  C1_w  'd28
`define  C1_s  'd784
`define  S2_h  'd14
`define  S2_w  'd14
`define  S2_s  'd196
`define  C3_h  'd12 
`define  C3_w  'd12
`define  C3_s  'd144
`define  S4_h  'd6 
`define  S4_w  'd6
`define  S4_s  'd36 
`define  C5_h  'd576
`define  F6_h  'd128
`define  out_h 'd10 
 

//channel num
`define img_c   'd1 
`define C1_c    'd8
`define C3_c    'd16

src/hw/fpga/ReLU.v
`include "Define.v"

module ReLU (data_in,data_out);
    input signed [`psum_wid-1:0] data_in;
    output signed [`psum_wid-1:0] data_out;

    assign data_out = (data_in > $signed('d0)) ? data_in : 'd0;

endmodule

src/ASIC/testbench/tb_ReLU.v
`timescale 1ns/10ps
`include "ReLU.v"

`define CYCLE 10 

module tb_ReLU;
reg clk;
reg rst;
reg signed [`psum_wid-1:0] data_in;
wire signed [`psum_wid-1:0] data_out;

ReLU relu
(
    .data_in(data_in),
    .data_out(data_out)
);

always #(`CYCLE/2) clk=~clk;

initial begin
        clk<=1'b1;
    #(`CYCLE*1) data_in = 'd5;
    #(`CYCLE*1) data_in = 'd8;
    #(`CYCLE*1) data_in = 'd10;
    #(`CYCLE*1) data_in = 'd6985;
    #(`CYCLE*1) data_in = 'd4421;
    #(`CYCLE*1) data_in = -'d8;
    #(`CYCLE*1) data_in = 'd8;
    #(`CYCLE*1) data_in = -'d5487;
    #(`CYCLE*1) data_in = 'd6985;
    #(`CYCLE*1) data_in = -'d8745;
    $finish;
end

initial begin
    $dumpfile("tb_ReLU.vcd");
    $dumpvars(0, tb_ReLU);
end

always @(*) begin
    $display($time, "data_out:  %d",data_out);
end

endmodule

src/hw/testbench/tb_ReLU.vcd
$date
	Sat Aug 26 15:53:07 2023
$end
$version
	Icarus Verilog
$end
$timescale
	10ps
$end
$scope module tb_ReLU $end
$var wire 32 ! data_out [31:0] $end
$var reg 1 " clk $end
$var reg 32 # data_in [31:0] $end
$scope module relu $end
$var wire 32 $ data_in [31:0] $end
$var wire 32 % data_out [31:0] $end
$upscope $end
$upscope $end
$enddefinitions $end
#0
$dumpvars
bx %
bx $
bx #
1"
bx !
$end
#500
0"
#1000
b101 !
b101 %
1"
b101 #
b101 $
#1500
0"
#2000
b1000 !
b1000 %
1"
b1000 #
b1000 $
#2500
0"
#3000
b1010 !
b1010 %
1"
b1010 #
b1010 $
#3500
0"
#4000
b1101101001001 !
b1101101001001 %
1"
b1101101001001 #
b1101101001001 $
#4500
0"
#5000
b1000101000101 !
b1000101000101 %
1"
b1000101000101 #
b1000101000101 $
#5500
0"
#6000
b0 !
b0 %
1"
b11111111111111111111111111111000 #
b11111111111111111111111111111000 $
#6500
0"
#7000
b1000 !
b1000 %
1"
b1000 #
b1000 $
#7500
0"
#8000
b0 !
b0 %
1"
b11111111111111111110101010010001 #
b11111111111111111110101010010001 $
#8500
0"
#9000
b1101101001001 !
b1101101001001 %
1"
b1101101001001 #
b1101101001001 $
#9500
0"
#10000
b0 !
b0 %
1"
b11111111111111111101110111010111 #
b11111111111111111101110111010111 $
